<?xml version="1.0"?>
<opencv_storage>
<calibration_Time>"Sun 05 Jan 2020 03:50:06 PM MST"</calibration_Time>
<nrOfFrames>15</nrOfFrames>
<image_Width>1280</image_Width>
<image_Height>720</image_Height>
<board_Width>4</board_Width>
<board_Height>11</board_Height>
<square_Size>15.</square_Size>
<FixAspectRatio>1.</FixAspectRatio>
<flagValue>14</flagValue>
<Camera_Matrix type_id="opencv-matrix">
  <rows>3</rows>
  <cols>3</cols>
  <dt>d</dt>
  <data>
    1.0015520728435985e+03 0. 640. 0. 1.0015520728435985e+03 360. 0. 0.
    1.</data></Camera_Matrix>
<Distortion_Coefficients type_id="opencv-matrix">
  <rows>5</rows>
  <cols>1</cols>
  <dt>d</dt>
  <data>
    1.6685903587192646e-01 -2.6917633714866579e-01 0. 0.
    1.3229445698578438e-01</data></Distortion_Coefficients>
<Avg_Reprojection_Error>1.1770391224464534e+00</Avg_Reprojection_Error>
<Per_View_Reprojection_Errors type_id="opencv-matrix">
  <rows>15</rows>
  <cols>1</cols>
  <dt>f</dt>
  <data>
    9.80134666e-01 9.33944285e-01 8.10228407e-01 9.51799273e-01
    1.17467177e+00 9.60732043e-01 1.12193668e+00 1.28538167e+00
    1.23191404e+00 7.40368664e-01 1.46353316e+00 1.20738626e+00
    1.75837672e+00 1.61405385e+00 8.99818182e-01</data></Per_View_Reprojection_Errors>
<Extrinsic_Parameters type_id="opencv-matrix">
  <rows>15</rows>
  <cols>6</cols>
  <dt>d</dt>
  <data>
    -1.7220916742061457e-02 1.9596082535433956e-01
    1.5509006383616930e+00 9.2537117031900422e+01
    -1.0254860600738479e+02 4.1321770247563421e+02
    -3.9370088686716855e-02 1.9109889988653905e-01
    1.5545298011137165e+00 9.2330442016512464e+01
    -1.1156689857365515e+02 4.1622902897837645e+02
    -8.3490295234472475e-02 -1.0955289459869043e-01
    1.5795134355416893e+00 -7.9342459946140778e+01
    -5.8095712810445278e+01 4.5379500323896070e+02
    -8.0717679668701497e-02 -8.2373474631859275e-02
    1.5780738764289597e+00 -7.8905073435806258e+01
    -5.8950249853215404e+01 4.5377423941020339e+02
    -7.5224292138708584e-02 -2.4398140320557659e-02
    1.5834119436454581e+00 -8.3394395338336409e+01
    -5.9202098869742692e+01 4.5408573933157231e+02
    1.8741428520374839e-01 1.7524564922351150e-02 1.6066654607363053e+00
    2.3890044240075989e+02 -3.9237209072420050e+01
    3.9987872602825098e+02 1.6465368374834474e-01 3.6295889834244900e-02
    1.6059618093679640e+00 2.2524689089957138e+02
    -3.8960529146387415e+01 4.0285986439174934e+02
    1.3244969255929068e-01 9.3870055909875669e-02 1.6027697030619035e+00
    2.2181498034958085e+02 -3.9611159898157347e+01
    4.0666997058477449e+02 -2.4339613509907067e-02
    -8.3151990128481026e-02 1.5592938381702024e+00
    9.0403703017962457e+01 1.2984791083635510e+01 4.1130024457604947e+02
    -1.0408538342796683e-01 -3.1503348428265611e-02
    1.5675610560172091e+00 8.8337395089938255e+01 5.7298584528274370e+00
    4.1718189502963247e+02 -1.9717359676377971e-01
    1.0784944953915898e-01 1.6048966503843045e+00 1.2278280388029337e+02
    -2.4193708008315763e+01 4.2744859117098537e+02
    -1.2600031147089419e-01 6.7223604150126140e-02
    1.5994172854712456e+00 1.2397130704545462e+02
    -2.9412577355986961e+01 4.3319123945212709e+02
    -1.1569679871941715e-01 -6.2514060475311342e-02
    1.5796612199845668e+00 1.1849096951638650e+02
    -3.0859057738682711e+01 4.3340942279465116e+02
    -7.5588911382400720e-03 1.0004646932345061e-01
    1.5484183780899152e+00 3.4068265788256028e+01
    -2.0245188724930632e+01 4.1891679251546503e+02
    -2.5816367710218414e-03 -3.2753909227033452e-02
    1.5237691467100847e+00 1.8302910437305492e+01
    -2.1244214527184269e+01 4.3666865487984069e+02</data></Extrinsic_Parameters>
<Image_points type_id="opencv-matrix">
  <rows>15</rows>
  <cols>44</cols>
  <dt>"2f"</dt>
  <data>
    8.68587463e+02 1.08185326e+02 8.70899902e+02 1.79862137e+02
    8.72703003e+02 2.52909668e+02 8.73378723e+02 3.27055481e+02
    8.31610779e+02 1.45572510e+02 8.33638062e+02 2.17442871e+02
    8.34714905e+02 2.91163818e+02 8.36020447e+02 3.64636139e+02
    7.93139282e+02 1.12252945e+02 7.94891541e+02 1.82972397e+02
    7.96281067e+02 2.55540237e+02 7.97471558e+02 3.28682861e+02
    7.56750427e+02 1.49316757e+02 7.58084900e+02 2.20465485e+02
    7.59262634e+02 2.93144867e+02 7.60569153e+02 3.66035950e+02
    7.19468628e+02 1.16656624e+02 7.20438049e+02 1.86240295e+02
    7.21607422e+02 2.58004791e+02 7.22716187e+02 3.30531128e+02
    6.83520996e+02 1.53424469e+02 6.84211792e+02 2.23455048e+02
    6.85294189e+02 2.95486725e+02 6.86646179e+02 3.67379333e+02
    6.47253906e+02 1.21013855e+02 6.47421448e+02 1.89678864e+02
    6.48133057e+02 2.60516724e+02 6.49584045e+02 3.32424133e+02
    6.11565430e+02 1.57044861e+02 6.11655273e+02 2.26139435e+02
    6.12771362e+02 2.97452637e+02 6.14419067e+02 3.68725098e+02
    5.76462830e+02 1.25191849e+02 5.75958069e+02 1.93041245e+02
    5.76204407e+02 2.62776276e+02 5.77981018e+02 3.33992462e+02
    5.41214111e+02 1.60895828e+02 5.40523499e+02 2.28824936e+02
    5.41494873e+02 2.99327942e+02 5.43458252e+02 3.70122131e+02
    5.06612671e+02 1.28597122e+02 5.06070282e+02 1.96526733e+02
    5.05160828e+02 2.64846191e+02 5.07343292e+02 3.35689484e+02
    8.66028564e+02 8.80833359e+01 8.68432434e+02 1.58201614e+02
    8.70245178e+02 2.30676147e+02 8.71258179e+02 3.04520142e+02
    8.29562988e+02 1.24515083e+02 8.31508850e+02 1.95363007e+02
    8.32614868e+02 2.68610687e+02 8.33981323e+02 3.42083527e+02
    7.91456055e+02 9.17561569e+01 7.93161804e+02 1.61019562e+02
    7.94594421e+02 2.33039780e+02 7.95662415e+02 3.05980682e+02
    7.55324280e+02 1.27761971e+02 7.56746521e+02 1.97897491e+02
    7.57702271e+02 2.70413330e+02 7.58797363e+02 3.43402985e+02
    7.18309082e+02 9.54007263e+01 7.19281006e+02 1.63970932e+02
    7.20207581e+02 2.35195358e+02 7.21129150e+02 3.07730927e+02
    6.82454346e+02 1.31040909e+02 6.83074951e+02 2.00558594e+02
    6.83891724e+02 2.72455841e+02 6.84925659e+02 3.44763977e+02
    6.46373596e+02 9.90398026e+01 6.46535095e+02 1.67127411e+02
    6.47041565e+02 2.37355286e+02 6.47892456e+02 3.09453522e+02
    6.10772400e+02 1.34318390e+02 6.10594543e+02 2.03063385e+02
    6.11363525e+02 2.74375153e+02 6.12578613e+02 3.46163727e+02
    5.75563660e+02 1.02693459e+02 5.75019836e+02 1.69909088e+02
    5.74998657e+02 2.39536285e+02 5.76076965e+02 3.11050629e+02
    5.40422668e+02 1.37933517e+02 5.39274170e+02 2.05380554e+02
    5.39794678e+02 2.76139740e+02 5.41217651e+02 3.47453217e+02
    5.06098816e+02 1.06490250e+02 5.04830536e+02 1.72887741e+02
    5.03696899e+02 2.41238037e+02 5.05143829e+02 3.12537933e+02
    4.64171906e+02 2.31606918e+02 4.64079803e+02 2.97989075e+02
    4.63371857e+02 3.63889496e+02 4.62316162e+02 4.29987671e+02
    4.29710663e+02 2.63987488e+02 4.29517578e+02 3.30520264e+02
    4.28671692e+02 3.96873779e+02 4.27290497e+02 4.63703491e+02
    3.94505859e+02 2.29012909e+02 3.95025055e+02 2.96488708e+02
    3.94444946e+02 3.63364838e+02 3.93346527e+02 4.30263733e+02
    3.59374542e+02 2.61770813e+02 3.59655121e+02 3.29365479e+02
    3.58740051e+02 3.96693939e+02 3.56921967e+02 4.64525330e+02
    3.22730011e+02 2.26277985e+02 3.23753571e+02 2.94855194e+02
    3.23509521e+02 3.62776031e+02 3.22210266e+02 4.30770721e+02
    2.86892303e+02 2.59684570e+02 2.87483429e+02 3.28341003e+02
    2.86761078e+02 3.96701691e+02 2.84513855e+02 4.65462433e+02
    2.49171783e+02 2.23722092e+02 2.50525635e+02 2.93302643e+02
    2.50683182e+02 3.62245422e+02 2.49110733e+02 4.31280518e+02
    2.12761459e+02 2.57616333e+02 2.13771072e+02 3.27260529e+02
    2.13118576e+02 3.96481720e+02 2.10680161e+02 4.66204010e+02
    1.74387192e+02 2.21515228e+02 1.76072662e+02 2.91836426e+02
    1.76770096e+02 3.61655640e+02 1.74978104e+02 4.31389709e+02
    1.37701187e+02 2.55817825e+02 1.39218643e+02 3.26144836e+02
    1.38442047e+02 3.96265656e+02 1.35910767e+02 4.66879639e+02
    9.91054688e+01 2.19124725e+02 1.00651939e+02 2.90396973e+02
    1.01747520e+02 3.61113556e+02 9.97732315e+01 4.31477417e+02
    4.65437195e+02 2.29460815e+02 4.65211761e+02 2.96140381e+02
    4.64384796e+02 3.62125916e+02 4.63253174e+02 4.28214050e+02
    4.30848846e+02 2.61992615e+02 4.30601654e+02 3.28688293e+02
    4.29666168e+02 3.95121674e+02 4.27914734e+02 4.62102448e+02
    3.95840454e+02 2.27183395e+02 3.96238586e+02 2.94712524e+02
    3.95641724e+02 3.61605286e+02 3.94163361e+02 4.28508087e+02
    3.60666809e+02 2.60062897e+02 3.60926483e+02 3.27693878e+02
    3.59903931e+02 3.94866791e+02 3.57522339e+02 4.62835938e+02
    3.24345032e+02 2.24661743e+02 3.25266144e+02 2.93200104e+02
    3.24895630e+02 3.61089539e+02 3.23151031e+02 4.28992371e+02
    2.88551025e+02 2.58198608e+02 2.89136353e+02 3.26716461e+02
    2.88294617e+02 3.95009216e+02 2.85346497e+02 4.63609344e+02
    2.51114548e+02 2.22390610e+02 2.52592041e+02 2.91857605e+02
    2.52571945e+02 3.60571442e+02 2.50449036e+02 4.29363739e+02
    2.14922638e+02 2.56421814e+02 2.16155441e+02 3.25801514e+02
    2.15090622e+02 3.94763306e+02 2.12196976e+02 4.64342346e+02
    1.76861328e+02 2.20475983e+02 1.78505386e+02 2.90532227e+02
    1.79258438e+02 3.60006470e+02 1.77041626e+02 4.29460266e+02
    1.40564911e+02 2.54765289e+02 1.42203232e+02 3.24957916e+02
    1.41495209e+02 3.94612488e+02 1.38035080e+02 4.64883484e+02
    1.02719864e+02 2.18635284e+02 1.04143120e+02 2.89301025e+02
    1.05139832e+02 3.59593536e+02 1.02354576e+02 4.29802979e+02
    4.55819336e+02 2.28572067e+02 4.55068756e+02 2.95341614e+02
    4.53322083e+02 3.61580383e+02 4.50952484e+02 4.27964050e+02
    4.21021790e+02 2.61196503e+02 4.19916260e+02 3.27864075e+02
    4.17985474e+02 3.94321167e+02 4.14798096e+02 4.61515839e+02
    3.86382355e+02 2.26262054e+02 3.86056885e+02 2.93757751e+02
    3.84457825e+02 3.60667938e+02 3.81763275e+02 4.27710449e+02
    3.51142609e+02 2.59171753e+02 3.50534302e+02 3.26669952e+02
    3.48351990e+02 3.93815948e+02 3.44469910e+02 4.61613770e+02
    3.15413666e+02 2.23929901e+02 3.15549500e+02 2.92219543e+02
    3.14250519e+02 3.59784790e+02 3.11128143e+02 4.27593475e+02
    2.79718628e+02 2.57147980e+02 2.79444427e+02 3.25472870e+02
    2.77324799e+02 3.93491364e+02 2.72834015e+02 4.61803070e+02
    2.43334366e+02 2.21675110e+02 2.43866409e+02 2.90715088e+02
    2.42840240e+02 3.59029358e+02 2.39425583e+02 4.27336426e+02
    2.07308823e+02 2.55400604e+02 2.07381851e+02 3.24269928e+02
    2.05300278e+02 3.92830505e+02 2.00508057e+02 4.61688660e+02
    1.70414764e+02 2.19641357e+02 1.71210632e+02 2.89222443e+02
    1.70770142e+02 3.58110168e+02 1.67048172e+02 4.26952545e+02
    1.34475861e+02 2.53673279e+02 1.35109695e+02 3.23238983e+02
    1.33034027e+02 3.92084839e+02 1.28129700e+02 4.61605774e+02
    9.81774445e+01 2.17836258e+02 9.85863724e+01 2.87925262e+02
    9.85090408e+01 3.57103943e+02 9.43902283e+01 4.26542084e+02
    1.25859485e+03 2.57530396e+02 1.24953796e+03 3.35035583e+02
    1.24135303e+03 4.11108429e+02 1.23435059e+03 4.87045197e+02
    1.21194556e+03 2.95335449e+02 1.20306213e+03 3.71095520e+02
    1.19704858e+03 4.47107605e+02 1.19040723e+03 5.22217163e+02
    1.17475830e+03 2.55752289e+02 1.16579980e+03 3.31823425e+02
    1.15885608e+03 4.06920959e+02 1.15337744e+03 4.82108765e+02
    1.12898840e+03 2.92956573e+02 1.12135291e+03 3.67530304e+02
    1.11569202e+03 4.42205109e+02 1.11025879e+03 5.16732422e+02
    1.09232446e+03 2.54232391e+02 1.08452759e+03 3.28870605e+02
    1.07831653e+03 4.02800446e+02 1.07342212e+03 4.76896759e+02
    1.04813696e+03 2.90691528e+02 1.04147754e+03 3.64179504e+02
    1.03633984e+03 4.37532959e+02 1.03157483e+03 5.11006317e+02
    1.01207306e+03 2.52919754e+02 1.00533466e+03 3.26160431e+02
    9.99738403e+02 3.98719421e+02 9.95258118e+02 4.71613403e+02
    9.69444519e+02 2.88752960e+02 9.63658325e+02 3.60779633e+02
    9.59187927e+02 4.32790314e+02 9.54631348e+02 5.05129944e+02
    9.33892456e+02 2.51685516e+02 9.28326294e+02 3.23516632e+02
    9.23440918e+02 3.94888062e+02 9.19171265e+02 4.66434692e+02
    8.93603882e+02 2.86826691e+02 8.88689087e+02 3.57600189e+02
    8.84199829e+02 4.28271729e+02 8.79848083e+02 4.99273163e+02
    8.59004333e+02 2.50513153e+02 8.54465759e+02 3.21070801e+02
    8.49836243e+02 3.91005585e+02 8.45563721e+02 4.61414307e+02
    1.21874023e+03 2.59966339e+02 1.21046301e+03 3.36506134e+02
    1.20263489e+03 4.11814850e+02 1.19841443e+03 4.87492371e+02
    1.17317322e+03 2.97430664e+02 1.16462939e+03 3.72377563e+02
    1.15947620e+03 4.47396332e+02 1.15686572e+03 5.23081177e+02
    1.13625110e+03 2.58224640e+02 1.12772363e+03 3.33588898e+02
    1.12136108e+03 4.07886810e+02 1.11765076e+03 4.82622528e+02
    1.09127649e+03 2.95045349e+02 1.08404114e+03 3.69058868e+02
    1.07936682e+03 4.43039001e+02 1.07704260e+03 5.17886719e+02
    1.05479724e+03 2.56709808e+02 1.04741211e+03 3.30677795e+02
    1.04176599e+03 4.03998352e+02 1.03853699e+03 4.77875183e+02
    1.01114386e+03 2.92905701e+02 1.00490570e+03 3.65730438e+02
    1.00103082e+03 4.38717438e+02 9.98571533e+02 5.12570862e+02
    9.75224609e+02 2.55278442e+02 9.68862122e+02 3.28098053e+02
    9.64158386e+02 4.00196167e+02 9.61181702e+02 4.73017273e+02
    9.33250549e+02 2.90901672e+02 9.28059265e+02 3.62581635e+02
    9.24547363e+02 4.34365875e+02 9.21957214e+02 5.07154327e+02
    8.98062073e+02 2.53988876e+02 8.92944763e+02 3.25412994e+02
    8.88928284e+02 3.96503479e+02 8.85788757e+02 4.68169037e+02
    8.58404175e+02 2.88996307e+02 8.54126282e+02 3.59446381e+02
    8.50553772e+02 4.30261871e+02 8.47565674e+02 5.01817810e+02
    8.23918701e+02 2.52625641e+02 8.20030457e+02 3.23069214e+02
    8.16183594e+02 3.93034302e+02 8.12783508e+02 4.63541382e+02
    1.20448523e+03 2.60007111e+02 1.19846289e+03 3.36339691e+02
    1.19239160e+03 4.11195160e+02 1.19049927e+03 4.86717987e+02
    1.16061609e+03 2.97389252e+02 1.15378833e+03 3.72163147e+02
    1.15038977e+03 4.46860992e+02 1.15072302e+03 5.22600647e+02
    1.12277246e+03 2.58510040e+02 1.11619348e+03 3.33568390e+02
    1.11156091e+03 4.07666901e+02 1.11007056e+03 4.82192657e+02
    1.07886279e+03 2.95338806e+02 1.07352026e+03 3.69073700e+02
    1.07058521e+03 4.42859955e+02 1.07076904e+03 5.17593811e+02
    1.04148206e+03 2.57294891e+02 1.03592688e+03 3.31021667e+02
    1.03231653e+03 4.04056458e+02 1.03109009e+03 4.77779266e+02
    9.98822693e+02 2.93516602e+02 9.94523621e+02 3.66062103e+02
    9.92504333e+02 4.38824402e+02 9.92261597e+02 5.12518311e+02
    9.62017090e+02 2.56259308e+02 9.57568237e+02 3.28657440e+02
    9.54831238e+02 4.00598511e+02 9.53782898e+02 4.73186127e+02
    9.21235291e+02 2.91802765e+02 9.18082153e+02 3.63176300e+02
    9.16290100e+02 4.34791504e+02 9.15620300e+02 5.07407288e+02
    8.85279053e+02 2.55232559e+02 8.82120361e+02 3.26337372e+02
    8.79787598e+02 3.97238586e+02 8.78626648e+02 4.68644714e+02
    8.46691589e+02 2.90112000e+02 8.44347046e+02 3.60301697e+02
    8.42486267e+02 4.30837006e+02 8.41219727e+02 5.02356293e+02
    8.11381165e+02 2.53961716e+02 8.09328369e+02 3.24218170e+02
    8.07280701e+02 3.94021637e+02 8.05769958e+02 4.64254974e+02
    8.59644775e+02 3.93929810e+02 8.61781433e+02 4.65462036e+02
    8.64631409e+02 5.38497498e+02 8.64206482e+02 6.10731201e+02
    8.24112122e+02 4.29899475e+02 8.27387695e+02 5.02585358e+02
    8.28265015e+02 5.75594421e+02 8.28214355e+02 6.48606750e+02
    7.87281677e+02 3.94414886e+02 7.89036804e+02 4.66403320e+02
    7.91429810e+02 5.39630615e+02 7.91837830e+02 6.13113159e+02
    7.51552307e+02 4.30750885e+02 7.53905640e+02 5.03523132e+02
    7.54899109e+02 5.77240601e+02 7.55225037e+02 6.50958740e+02
    7.14748169e+02 3.95201111e+02 7.16065918e+02 4.67290741e+02
    7.17646362e+02 5.41170898e+02 7.18113403e+02 6.15149048e+02
    6.78571411e+02 4.31526154e+02 6.80001343e+02 5.04776489e+02
    6.80772949e+02 5.78974304e+02 6.80951599e+02 6.53158142e+02
    6.41691589e+02 3.95866302e+02 6.42381592e+02 4.68503967e+02
    6.43226440e+02 5.42711792e+02 6.43450745e+02 6.17047241e+02
    6.05004333e+02 4.32614136e+02 6.05593018e+02 5.06372528e+02
    6.05846313e+02 5.80943054e+02 6.05787415e+02 6.55959106e+02
    5.67813660e+02 3.97040527e+02 5.67998047e+02 4.70003174e+02
    5.67961670e+02 5.44549500e+02 5.67948669e+02 6.19578857e+02
    5.30258850e+02 4.33768433e+02 5.30116394e+02 5.08108215e+02
    5.29843750e+02 5.83118713e+02 5.29730896e+02 6.58783447e+02
    4.92397705e+02 3.97852966e+02 4.92003357e+02 4.71844086e+02
    4.91572540e+02 5.46806946e+02 4.91269379e+02 6.22143372e+02
    8.52250549e+02 3.74057892e+02 8.55315002e+02 4.46462006e+02
    8.57908264e+02 5.20433655e+02 8.57424622e+02 5.94152222e+02
    8.17587708e+02 4.10059174e+02 8.20961304e+02 4.83503082e+02
    8.21526001e+02 5.57927795e+02 8.21319397e+02 6.32448303e+02
    7.80726379e+02 3.74137329e+02 7.83126404e+02 4.46613159e+02
    7.84963379e+02 5.21039917e+02 7.85151245e+02 5.95874023e+02
    7.45576782e+02 4.10219940e+02 7.47800049e+02 4.83899506e+02
    7.48322632e+02 5.58766846e+02 7.48419861e+02 6.34227478e+02
    7.08828613e+02 3.74230347e+02 7.10251221e+02 4.46961517e+02
    7.11455383e+02 5.21692322e+02 7.11484070e+02 5.97066772e+02
    6.73110596e+02 4.10553162e+02 6.74263550e+02 4.84439972e+02
    6.74534424e+02 5.59902527e+02 6.74342041e+02 6.35739380e+02
    6.36641846e+02 3.74317383e+02 6.37114868e+02 4.47516479e+02
    6.37401428e+02 5.22615723e+02 6.37134827e+02 5.98432373e+02
    6.00252075e+02 4.10896881e+02 6.00248657e+02 4.85310120e+02
    5.99839111e+02 5.61054504e+02 5.99366638e+02 6.37835815e+02
    5.63621460e+02 3.74503601e+02 5.63170410e+02 4.48208466e+02
    5.62577271e+02 5.23745300e+02 5.61922119e+02 6.00111450e+02
    5.26224609e+02 4.11432190e+02 5.25224243e+02 4.86344177e+02
    5.24381104e+02 5.62563110e+02 5.23344116e+02 6.39902893e+02
    4.89062378e+02 3.74807709e+02 4.87981750e+02 4.49191650e+02
    4.86646637e+02 5.25111328e+02 4.85520477e+02 6.02023621e+02
    9.29313049e+02 3.04046417e+02 9.34421082e+02 3.72658997e+02
    9.36989441e+02 4.44943909e+02 9.34400208e+02 5.18742981e+02
    8.96037476e+02 3.36115692e+02 9.00138367e+02 4.06438721e+02
    8.99181763e+02 4.80220978e+02 8.97491333e+02 5.54674561e+02
    8.58584778e+02 3.00237640e+02 8.62235779e+02 3.68921448e+02
    8.63478943e+02 4.41486237e+02 8.61654175e+02 5.15714111e+02
    8.24648621e+02 3.32322601e+02 8.26754517e+02 4.02996704e+02
    8.26079285e+02 4.76911438e+02 8.24175415e+02 5.51563049e+02
    7.87598572e+02 2.96715576e+02 7.89595093e+02 3.65316925e+02
    7.89869690e+02 4.38185120e+02 7.88235046e+02 5.12487427e+02
    7.52716064e+02 3.29016174e+02 7.53329163e+02 3.99796783e+02
    7.52200684e+02 4.73561737e+02 7.50129700e+02 5.48073486e+02
    7.16621338e+02 2.93388733e+02 7.16987793e+02 3.62321655e+02
    7.16207947e+02 4.34837341e+02 7.14186401e+02 5.09020050e+02
    6.80723206e+02 3.25651886e+02 6.80183838e+02 3.96582794e+02
    6.78428345e+02 4.70280304e+02 6.76087708e+02 5.44635498e+02
    6.45418701e+02 2.90060028e+02 6.44368408e+02 3.59153625e+02
    6.42796692e+02 4.31685303e+02 6.40338074e+02 5.05751129e+02
    6.08788940e+02 3.22738281e+02 6.07138977e+02 3.93454559e+02
    6.04824463e+02 4.67186188e+02 6.02218872e+02 5.41233337e+02
    5.73847473e+02 2.86325439e+02 5.71733948e+02 3.56100128e+02
    5.68997742e+02 4.28653473e+02 5.66614624e+02 5.02672516e+02
    9.28793945e+02 2.93670471e+02 9.31651794e+02 3.61256073e+02
    9.33017029e+02 4.31302063e+02 9.30156616e+02 5.02338318e+02
    8.95005432e+02 3.25737091e+02 8.97335571e+02 3.94660187e+02
    8.95827637e+02 4.65824005e+02 8.94306763e+02 5.37502319e+02
    8.59307983e+02 2.90578369e+02 8.60882446e+02 3.58424194e+02
    8.61145996e+02 4.29037415e+02 8.59308350e+02 5.00589264e+02
    8.24849670e+02 3.22785583e+02 8.25515625e+02 3.92168396e+02
    8.24418701e+02 4.63669159e+02 8.22916992e+02 5.35672241e+02
    7.89339111e+02 2.87806000e+02 7.89622314e+02 3.55774384e+02
    7.88944641e+02 4.26747009e+02 7.87562805e+02 4.98649109e+02
    7.54178284e+02 3.20242981e+02 7.53577148e+02 3.89794006e+02
    7.52292603e+02 4.61470673e+02 7.50677063e+02 5.33800293e+02
    7.19250183e+02 2.85209167e+02 7.18280396e+02 3.53625824e+02
    7.16969849e+02 4.24428955e+02 7.15319153e+02 4.96508331e+02
    6.83299500e+02 3.17884277e+02 6.81929016e+02 3.87634827e+02
    6.80281189e+02 4.59230255e+02 6.78582092e+02 5.31914124e+02
    6.49130676e+02 2.82527679e+02 6.47080688e+02 3.51290802e+02
    6.45183350e+02 4.22217712e+02 6.43314331e+02 4.94524475e+02
    6.12747498e+02 3.15480957e+02 6.10480774e+02 3.85390259e+02
    6.08194275e+02 4.57287720e+02 6.06290710e+02 5.30068542e+02
    5.78692017e+02 2.79738312e+02 5.75863281e+02 3.49046753e+02
    5.73237610e+02 4.20208923e+02 5.70980347e+02 4.92584930e+02
    9.13561707e+02 2.89463959e+02 9.18055847e+02 3.56954559e+02
    9.19946472e+02 4.27289429e+02 9.16370178e+02 4.98455719e+02
    8.81520142e+02 3.22251373e+02 8.85431946e+02 3.91261505e+02
    8.83493591e+02 4.62897736e+02 8.80871521e+02 5.34614868e+02
    8.45867737e+02 2.88136322e+02 8.49302002e+02 3.55680176e+02
    8.50217529e+02 4.26882721e+02 8.47485840e+02 4.98712616e+02
    8.13265320e+02 3.20903442e+02 8.15215881e+02 3.90674530e+02
    8.13973633e+02 4.62836426e+02 8.11499756e+02 5.35031616e+02
    7.77426575e+02 2.86638580e+02 7.79508179e+02 3.54896301e+02
    7.79622253e+02 4.26535583e+02 7.77507019e+02 4.98997589e+02
    7.43877747e+02 3.19869171e+02 7.44432617e+02 3.90040100e+02
    7.43037598e+02 4.62856476e+02 7.40772400e+02 5.35393982e+02
    7.08674744e+02 2.85465820e+02 7.09103455e+02 3.54344727e+02
    7.08396545e+02 4.26236450e+02 7.06433472e+02 4.99096619e+02
    6.73822388e+02 3.19006927e+02 6.73457153e+02 3.89792480e+02
    6.71740967e+02 4.62671997e+02 6.69469116e+02 5.36086182e+02
    6.39006287e+02 2.84243195e+02 6.38162903e+02 3.53802094e+02
    6.37015015e+02 4.25858459e+02 6.34783081e+02 4.99509064e+02
    6.03327148e+02 3.18292267e+02 6.01926636e+02 3.89352234e+02
    5.99743408e+02 4.62827606e+02 5.97505493e+02 5.36986023e+02
    5.68648132e+02 2.82898224e+02 5.66790466e+02 3.53035217e+02
    5.64654846e+02 4.25956635e+02 5.62208008e+02 5.00220978e+02
    7.25232422e+02 3.09913666e+02 7.25109619e+02 3.82875458e+02
    7.25258362e+02 4.55956665e+02 7.25574463e+02 5.27939575e+02
    6.88584106e+02 3.47288452e+02 6.88533386e+02 4.20296234e+02
    6.88770569e+02 4.92528656e+02 6.89298157e+02 5.65416016e+02
    6.52609436e+02 3.12236542e+02 6.52084595e+02 3.84598663e+02
    6.51921936e+02 4.57522919e+02 6.52679932e+02 5.29132629e+02
    6.16355713e+02 3.49451965e+02 6.15654724e+02 4.22047394e+02
    6.16341003e+02 4.94148438e+02 6.16872742e+02 5.66344788e+02
    5.80836853e+02 3.14410767e+02 5.79991699e+02 3.86575653e+02
    5.79761536e+02 4.59216003e+02 5.80682312e+02 5.30747314e+02
    5.44582336e+02 3.51397644e+02 5.43706604e+02 4.23876923e+02
    5.44359314e+02 4.96029388e+02 5.45180847e+02 5.67682434e+02
    5.09520569e+02 3.16481171e+02 5.08372986e+02 3.88432587e+02
    5.07860291e+02 4.61178436e+02 5.09187408e+02 5.32640259e+02
    4.73334351e+02 3.53340424e+02 4.72162506e+02 4.25757324e+02
    4.72855621e+02 4.97847321e+02 4.73638885e+02 5.69741150e+02
    4.38204529e+02 3.18474548e+02 4.37021423e+02 3.90542542e+02
    4.36466248e+02 4.62999420e+02 4.37577545e+02 5.34716919e+02
    4.01995209e+02 3.55458374e+02 4.00877899e+02 4.27760590e+02
    4.01645020e+02 4.99756470e+02 4.02305786e+02 5.71804077e+02
    3.67352386e+02 3.20572266e+02 3.66250580e+02 3.92496307e+02
    3.65294464e+02 4.64952332e+02 3.66274017e+02 5.36788208e+02
    6.83664185e+02 3.10421783e+02 6.86224854e+02 3.79709503e+02
    6.88962402e+02 4.48680420e+02 6.91597412e+02 5.16606934e+02
    6.50138062e+02 3.46885681e+02 6.52753601e+02 4.16077057e+02
    6.55600037e+02 4.84297150e+02 6.58527100e+02 5.52995483e+02
    6.14320923e+02 3.13880707e+02 6.16799072e+02 3.83112335e+02
    6.19481384e+02 4.52288849e+02 6.22475891e+02 5.20141724e+02
    5.80936401e+02 3.50208771e+02 5.83282349e+02 4.19500946e+02
    5.86322998e+02 4.88020233e+02 5.89510010e+02 5.56526245e+02
    5.44931335e+02 3.17363617e+02 5.47271606e+02 3.86541229e+02
    5.49797668e+02 4.56040558e+02 5.53320374e+02 5.24058777e+02
    5.11368958e+02 3.53635986e+02 5.13334595e+02 4.23204620e+02
    5.16800476e+02 4.92075073e+02 5.20209106e+02 5.60574890e+02
    4.75142975e+02 3.20711273e+02 4.77291351e+02 3.90148499e+02
    4.79834686e+02 4.59849823e+02 4.83774475e+02 5.28196289e+02
    4.41136078e+02 3.57061890e+02 4.43120056e+02 4.26895844e+02
    4.46773560e+02 4.96086914e+02 4.50296387e+02 5.65182190e+02
    4.04751617e+02 3.24015869e+02 4.06895050e+02 3.93776306e+02
    4.09432312e+02 4.63754364e+02 4.13639587e+02 5.32519409e+02
    3.70626282e+02 3.60576416e+02 3.72429230e+02 4.30799652e+02
    3.76408539e+02 5.00191711e+02 3.80013702e+02 5.69911499e+02
    3.33968048e+02 3.27428192e+02 3.36097076e+02 3.97422638e+02
    3.38832855e+02 4.67707245e+02 3.43076050e+02 5.36977600e+02</data></Image_points>
</opencv_storage>
